otelib/__init__.py
otelib/client.py
otelib/exceptions.py
otelib/pipe.py
otelib/settings.py
otelib/warnings.py
otelib/backends/__init__.py
otelib/backends/client.py
otelib/backends/factories.py
otelib/backends/strategies.py
otelib/backends/utils.py
otelib/backends/python/__init__.py
otelib/backends/python/base.py
otelib/backends/python/client.py
otelib/backends/python/dataresource.py
otelib/backends/python/filter.py
otelib/backends/python/function.py
otelib/backends/python/mapping.py
otelib/backends/python/parser.py
otelib/backends/python/transformation.py
otelib/backends/services/__init__.py
otelib/backends/services/base.py
otelib/backends/services/client.py
otelib/backends/services/dataresource.py
otelib/backends/services/filter.py
otelib/backends/services/function.py
otelib/backends/services/mapping.py
otelib/backends/services/parser.py
otelib/backends/services/transformation.py
otelib-1.0.0.dist-info/licenses/LICENSE
otelib-1.0.0.dist-info/WHEEL
otelib-1.0.0.dist-info/METADATA
otelib-1.0.0.dist-info/RECORD
