Metadata-Version: 2.4
Name: otelib
Version: 1.0.0
Summary: Open Translation Environment (OTE) REST API client library.
Keywords: OTE,OTE-API
Author-email: SINTEF <TEAM4.0@SINTEF.no>
Requires-Python: ~=3.10
Classifier: Development Status :: 2 - Pre-Alpha
Classifier: License :: OSI Approved :: MIT License
Classifier: Programming Language :: Python :: 3
Classifier: Programming Language :: Python :: 3.10
Classifier: Programming Language :: Python :: 3.11
Classifier: Programming Language :: Python :: 3.12
Classifier: Programming Language :: Python :: 3.13
Classifier: Natural Language :: English
Classifier: Operating System :: OS Independent
License-File: LICENSE
Requires-Dist: oteapi-core >=1.0.0
Requires-Dist: pydantic-settings ~=2.8
Requires-Dist: pre-commit ~=4.2 ; extra == "dev"
Requires-Dist: pytest ~=8.3 ; extra == "dev"
Requires-Dist: pytest-cov ~=6.1 ; extra == "dev"
Requires-Dist: requests-mock ~=1.12 ; extra == "dev"
Project-URL: Changelog, https://github.com/EMMC-ASBL/otelib/blob/master/CHANGELOG.md
Project-URL: Documentation, https://EMMC-ASBL.github.io/otelib
Project-URL: Home, https://github.com/EMMC-ASBL/otelib
Project-URL: Issue Tracker, https://github.com/EMMC-ASBL/otelib/issues
Project-URL: Package, https://pypi.org/project/otelib
Project-URL: Source, https://github.com/EMMC-ASBL/otelib
Provides-Extra: dev
